df2d/dataset.py
df2d/inference.py
df2d/model.py
df2d/parser.py
df2d/util.py
nely_df2d-0.14.dist-info/METADATA
nely_df2d-0.14.dist-info/WHEEL
nely_df2d-0.14.dist-info/top_level.txt
nely_df2d-0.14.dist-info/RECORD
