Metadata-Version: 2.1
Name: nely-df2d
Version: 0.14
Summary: 2D pose estimation pipeline for tethered Drosophila.
Home-page: https://github.com/NeLy-EPFL/Drosophila2DPose
Author: Semih Gunel
Author-email: gunelsemih@gmail.com
License: UNKNOWN
Platform: UNKNOWN
